jupyterlab_broccoli_blocks/__init__.py
jupyterlab_broccoli_blocks/_version.py
jupyterlab_broccoli_blocks/labextension/build_log.json
jupyterlab_broccoli_blocks/labextension/package.json
jupyterlab_broccoli_blocks/labextension/static/lib_index_js.e0f51e9e8bbdda5163ad.js
jupyterlab_broccoli_blocks/labextension/static/lib_index_js.e0f51e9e8bbdda5163ad.js.map
jupyterlab_broccoli_blocks/labextension/static/lib_msg_En_js.5ede2a225d474257384e.js
jupyterlab_broccoli_blocks/labextension/static/lib_msg_En_js.5ede2a225d474257384e.js.map
jupyterlab_broccoli_blocks/labextension/static/lib_msg_Jp_js.ddb0e8dfc4dff1eef23c.js
jupyterlab_broccoli_blocks/labextension/static/lib_msg_Jp_js.ddb0e8dfc4dff1eef23c.js.map
jupyterlab_broccoli_blocks/labextension/static/node_modules_jupyterlab-broccoli_lib_msg_En_js.f58d725f5efb702d7cf5.js
jupyterlab_broccoli_blocks/labextension/static/node_modules_jupyterlab-broccoli_lib_msg_En_js.f58d725f5efb702d7cf5.js.map
jupyterlab_broccoli_blocks/labextension/static/node_modules_jupyterlab-broccoli_lib_msg_Jp_js.fce21f80be1d70daf26b.js
jupyterlab_broccoli_blocks/labextension/static/node_modules_jupyterlab-broccoli_lib_msg_Jp_js.fce21f80be1d70daf26b.js.map
jupyterlab_broccoli_blocks/labextension/static/node_modules_jupyterlab-broccoli_lib_msg_lazy_recursive_js_-_f9570.4871e9a52fa52c43cddc.js
jupyterlab_broccoli_blocks/labextension/static/node_modules_jupyterlab-broccoli_lib_msg_lazy_recursive_js_-_f9570.4871e9a52fa52c43cddc.js.map
jupyterlab_broccoli_blocks/labextension/static/node_modules_jupyterlab-broccoli_lib_msg_lazy_recursive_js_-_f9571.6a2274ef1d902e98a026.js
jupyterlab_broccoli_blocks/labextension/static/node_modules_jupyterlab-broccoli_lib_msg_lazy_recursive_js_-_f9571.6a2274ef1d902e98a026.js.map
jupyterlab_broccoli_blocks/labextension/static/remoteEntry.334c43163dfdd14f8d07.js
jupyterlab_broccoli_blocks/labextension/static/remoteEntry.334c43163dfdd14f8d07.js.map
jupyterlab_broccoli_blocks/labextension/static/style.js
jupyterlab_broccoli_blocks-0.4.6.dist-info/METADATA
jupyterlab_broccoli_blocks-0.4.6.dist-info/WHEEL
jupyterlab_broccoli_blocks-0.4.6.dist-info/licenses/LICENSE
jupyterlab_broccoli_blocks-0.4.6.dist-info/RECORD
