Metadata-Version: 2.1
Name: jupyterlab-broccoli-blocks
Version: 0.4.6
Summary: Template of Blockly extension for JupyterLab.
Project-URL: Homepage, https://github.com/FumiHax/jupyterlab-broccoli-blocks
Project-URL: Bug Tracker, https://github.com/FumiHax/jupyterlab-broccoli-blocks/issues
Project-URL: Repository, https://github.com/FumiHax/jupyterlab-broccoli-blocks.git
Author-email: "Fumi.Iseki" <iseki@rsch.tuis.ac.jp>
License: BSD 3-Clause License
License-File: LICENSE
Classifier: Framework :: Jupyter
Classifier: Framework :: Jupyter :: JupyterLab
Classifier: Framework :: Jupyter :: JupyterLab :: 3
Classifier: Framework :: Jupyter :: JupyterLab :: Extensions
Classifier: Framework :: Jupyter :: JupyterLab :: Extensions :: Prebuilt
Classifier: License :: OSI Approved :: BSD License
Classifier: Programming Language :: Python
Classifier: Programming Language :: Python :: 3
Classifier: Programming Language :: Python :: 3.7
Classifier: Programming Language :: Python :: 3.8
Classifier: Programming Language :: Python :: 3.9
Classifier: Programming Language :: Python :: 3.10
Classifier: Programming Language :: Python :: 3.11
Requires-Python: >=3.7
Requires-Dist: jupyterlab-broccoli>=0.4.6
